pygans/__init__.py
pygans/animation/__init__.py
pygans/animation/animation.py
pygans/animation/animation_2d.py
pygans/animation/animation_mnist.py
pygans/dataset/__init__.py
pygans/dataset/dataset_generator.py
pygans/dataset/dataset_generator_2d.py
pygans/dataset/dataset_generator_mnist.py
pygans/models/__init__.py
pygans/models/discriminator.py
pygans/models/gan.py
pygans/models/generator.py
pygans-2.0.3.dist-info/LICENSE
pygans-2.0.3.dist-info/METADATA
pygans-2.0.3.dist-info/WHEEL
pygans-2.0.3.dist-info/top_level.txt
pygans-2.0.3.dist-info/RECORD
