Metadata-Version: 2.1
Name: pygans
Version: 2.0.3
Summary: Simple Python Framework for creating GANs and seeing evolution through time
Home-page: https://gitlab.com/afzp99/pygans
Author: Andres Felipe Zapata Palacio
Author-email: afzp99@gmail.com
License: MIT
Platform: UNKNOWN
Classifier: License :: OSI Approved :: MIT License
Classifier: Programming Language :: Python :: 3
Classifier: Programming Language :: Python :: 3.6
Requires-Dist: numpy
Requires-Dist: keras
Requires-Dist: matplotlib
Requires-Dist: tensorflow
